{
  "style": {
    "font": "chữ in hoa lớn, serif máy chữ, đổ bóng nhẹ cho dễ đọc trên nền ảnh",
    "size": "chiếm khoảng 1/8 chiều cao khung — khán giả 65+ xem trên điện thoại phải đọc được",
    "speed": "gõ chậm, đều; âm gõ phím chạy đúng theo thời lượng cột Gõ (s) rồi dừng",
    "hold": "giữ dòng 1-2s sau khi gõ xong rồi mờ dần",
    "position": "1/3 dưới khung, tránh che mặt nhân vật"
  },
  "cues": [
    {
      "id": "tw01",
      "stt": 2,
      "at": "00:00:13",
      "type": "stat",
      "text": "$91,400",
      "sync": "gõ đúng lúc narration đọc con số đấu giá — cú móc đầu tiên của hook"
    },
    {
      "id": "tw02",
      "stt": 4,
      "at": "00:00:28",
      "type": "stat",
      "text": "22 YEARS",
      "sync": "đè lên hình đồi kudzu một màu — con số giải thích vì sao không ai trả giá"
    },
    {
      "id": "tw03",
      "stt": 18,
      "at": "00:02:58",
      "type": "stat",
      "text": "104 ACRES",
      "sync": "khi narration đọc mô tả thửa đất trong hồ sơ hạt"
    },
    {
      "id": "tw04",
      "stt": 26,
      "at": "00:04:23",
      "type": "stat",
      "text": "THREE GROWING SEASONS",
      "sync": "đồng hồ đếm ngược của cả phim — gõ chậm hơn các cue khác một nhịp"
    },
    {
      "id": "tw05",
      "stt": 41,
      "at": "00:07:00",
      "type": "stat",
      "text": "83 GOATS",
      "sync": "đúng lúc cổng mở và đàn dê tràn xuống"
    },
    {
      "id": "tw06",
      "stt": 58,
      "at": "00:10:00",
      "type": "stat",
      "text": "NINE TREES",
      "sync": "khoảnh khắc đếm xong — trả lời câu hỏi treo từ phút đầu của hook"
    },
    {
      "id": "tw07",
      "stt": 96,
      "at": "00:17:08",
      "type": "time_card",
      "text": "SUMMER TWO",
      "sync": "time card mở màn mùa hè thứ hai"
    },
    {
      "id": "tw08",
      "stt": 118,
      "at": "00:21:02",
      "type": "time_card",
      "text": "YEAR THREE",
      "sync": "time card mở màn năm thứ ba, lúc bắt đầu trồng cây"
    },
    {
      "id": "tw09",
      "stt": 137,
      "at": "00:24:27",
      "type": "time_card",
      "text": "SPRING, YEAR FOUR",
      "sync": "time card ngày hạt tới thẩm định — cao trào hành chính"
    },
    {
      "id": "tw10",
      "stt": 151,
      "at": "00:26:38",
      "type": "stat",
      "text": "$462,800",
      "sync": "định giá lại — đặt cạnh trí nhớ về $91,400 ở đầu phim"
    },
    {
      "id": "tw11",
      "stt": 156,
      "at": "00:27:32",
      "type": "stat",
      "text": "1,341 POUNDS",
      "sync": "vụ hồ đào đầu tiên sau 22 năm"
    },
    {
      "id": "tw12",
      "stt": 180,
      "at": "00:31:34",
      "type": "moral",
      "text": "NEVER DEAD GROUND — ONLY COVERED GROUND",
      "sync": "câu thesis của cả phim, gõ chậm nhất, giữ dòng lâu nhất trước khi mờ"
    }
  ],
  "notes": [
    "Chỉ 12 cue cho video 33 phút — dùng thưa để mỗi lần chữ hiện lên đều có sức nặng.",
    "Âm gõ phím CHỈ phát tại cột Time của từng cue và dừng sau đúng cột Gõ (s); scene không có trong bảng thì không có chữ và không có âm đánh chữ.",
    "Muốn thêm/sửa cue: chỉ sửa file này rồi chạy lại python3 scripts/export.py — KHÔNG sửa tay metadata.json hay typewriter-cues.md."
  ]
}
